sample_csv/__init__.py
sample_csv/main.py
sample_csv-1.0.1.dist-info/METADATA
sample_csv-1.0.1.dist-info/WHEEL
sample_csv-1.0.1.dist-info/entry_points.txt
sample_csv-1.0.1.dist-info/RECORD
